WaterMoleculeClassifier/__init__.py
WaterMoleculeClassifier/predictor.py
WaterMoleculeClassifier-1.1.dist-info/METADATA
WaterMoleculeClassifier-1.1.dist-info/WHEEL
WaterMoleculeClassifier-1.1.dist-info/top_level.txt
WaterMoleculeClassifier-1.1.dist-info/RECORD
