Metadata-Version: 2.1
Name: WaterMoleculeClassifier
Version: 1.1
Summary: UNKNOWN
Home-page: UNKNOWN
License: UNKNOWN
Platform: UNKNOWN
Requires-Dist: joblib
Requires-Dist: scikit-learn
Requires-Dist: pandas
